TensorflowShenduXuexiZhongwenDierBanChuyi/README.md
TensorflowShenduXuexiZhongwenDierBanChuyi/__init__.py
TensorflowShenduXuexiZhongwenDierBanChuyi/__main__.py
TensorflowShenduXuexiZhongwenDierBanChuyi/file.epub
TensorflowShenduXuexiZhongwenDierBanChuyi/index.html
TensorflowShenduXuexiZhongwenDierBanChuyi/css/__init__.py
TensorflowShenduXuexiZhongwenDierBanChuyi/css/annotations.css
TensorflowShenduXuexiZhongwenDierBanChuyi/css/main.css
TensorflowShenduXuexiZhongwenDierBanChuyi/css/normalize.css
TensorflowShenduXuexiZhongwenDierBanChuyi/css/popup.css
TensorflowShenduXuexiZhongwenDierBanChuyi/font/__init__.py
TensorflowShenduXuexiZhongwenDierBanChuyi/font/fontello.eot
TensorflowShenduXuexiZhongwenDierBanChuyi/font/fontello.svg
TensorflowShenduXuexiZhongwenDierBanChuyi/font/fontello.ttf
TensorflowShenduXuexiZhongwenDierBanChuyi/font/fontello.woff
TensorflowShenduXuexiZhongwenDierBanChuyi/img/__init__.py
TensorflowShenduXuexiZhongwenDierBanChuyi/img/annotator-glyph-sprite.png
TensorflowShenduXuexiZhongwenDierBanChuyi/img/annotator-icon-sprite.png
TensorflowShenduXuexiZhongwenDierBanChuyi/img/apple-touch-icon.png
TensorflowShenduXuexiZhongwenDierBanChuyi/img/cancelfullscreen.png
TensorflowShenduXuexiZhongwenDierBanChuyi/img/close.png
TensorflowShenduXuexiZhongwenDierBanChuyi/img/fullscreen.png
TensorflowShenduXuexiZhongwenDierBanChuyi/img/loader.gif
TensorflowShenduXuexiZhongwenDierBanChuyi/img/menu-icon.png
TensorflowShenduXuexiZhongwenDierBanChuyi/img/save.png
TensorflowShenduXuexiZhongwenDierBanChuyi/img/saved.png
TensorflowShenduXuexiZhongwenDierBanChuyi/img/settings-s.png
TensorflowShenduXuexiZhongwenDierBanChuyi/img/settings.png
TensorflowShenduXuexiZhongwenDierBanChuyi/img/star.png
TensorflowShenduXuexiZhongwenDierBanChuyi/js/__init__.py
TensorflowShenduXuexiZhongwenDierBanChuyi/js/epub.js
TensorflowShenduXuexiZhongwenDierBanChuyi/js/epub.min.js
TensorflowShenduXuexiZhongwenDierBanChuyi/js/epub.min.map
TensorflowShenduXuexiZhongwenDierBanChuyi/js/hooks.min.js
tensorflow_shendu_xuexi_zhongwen_dier_ban_chuyi-2024.3.5.0.dist-info/METADATA
tensorflow_shendu_xuexi_zhongwen_dier_ban_chuyi-2024.3.5.0.dist-info/WHEEL
tensorflow_shendu_xuexi_zhongwen_dier_ban_chuyi-2024.3.5.0.dist-info/entry_points.txt
tensorflow_shendu_xuexi_zhongwen_dier_ban_chuyi-2024.3.5.0.dist-info/top_level.txt
tensorflow_shendu_xuexi_zhongwen_dier_ban_chuyi-2024.3.5.0.dist-info/RECORD
